gwp/__init__.py
gwp-0.2.0.dist-info/AUTHORS.rst
gwp-0.2.0.dist-info/LICENSE
gwp-0.2.0.dist-info/METADATA
gwp-0.2.0.dist-info/WHEEL
gwp-0.2.0.dist-info/top_level.txt
gwp-0.2.0.dist-info/RECORD
