Metadata-Version: 2.1
Name: gwp
Version: 0.2.0
Summary: Gabor Wavelet Pyramid model for tensorflow
Home-page: https://github.com/jooh/gwp
Author: Johan Carlin
Author-email: johan.carlin@gmail.com
License: MIT license
Keywords: gwp
Platform: UNKNOWN
Classifier: Development Status :: 2 - Pre-Alpha
Classifier: Intended Audience :: Developers
Classifier: License :: OSI Approved :: MIT License
Classifier: Natural Language :: English
Classifier: Programming Language :: Python :: 3.6
Classifier: Programming Language :: Python :: 3.7
Requires-Dist: numpy
Requires-Dist: tensorflow
Requires-Dist: scikit-image
